{
  "structure": {
    "attribute": "六属性",
    "meisuu": "命数（1-60）",
    "hand": "手相タイプ",
    "action": "行動タイプ（支援/自由/統率等）"
  },

  "sections": {
    "summary": "総合まとめ（属性×命数の核）",
    "core": "根本性質（属性の性格傾向）",
    "mission": "命数が示す使命・方向性",
    "behavior": "行動パターン（手相×行動型）",
    "strength": "強み（統合）",
    "weakness": "弱み（統合）",
    "advice": "現実的アドバイス",
    "story": "過去ストーリー言い当て"
  },

  "attribute_hooks": {
    "fire": {
      "theme": "直感と突破力",
      "style": "勢い・行動・リーダー性",
      "summary": "情熱が性格の中心にあり、直感で道を切り開く傾向が強い。"
    },
    "water": {
      "theme": "調和と共感",
      "style": "支援・理解・癒し",
      "summary": "人や環境との調和を最優先し、周囲を整える役割に立ちやすい。"
    },
    "wind": {
      "theme": "情報と知性",
      "style": "柔軟・多才・知的好奇心",
      "summary": "情報の扱いに長け、複数の分野を横断する軽さと速さがある。"
    },
    "sky": {
      "theme": "客観と俯瞰",
      "style": "分析・静けさ・論理性",
      "summary": "冷静な視点があり、全体像を把握してから動くタイプ。"
    },
    "dark": {
      "theme": "洞察と深み",
      "style": "探求・本質・再生",
      "summary": "表に見えるものより、裏側の本質を重視して判断する傾向。"
    },
    "light": {
      "theme": "希望と発信",
      "style": "魅力・直感・外向的",
      "summary": "周囲を照らすように、自然と人が集まってくるタイプ。"
    }
  },

  "meisuu_hooks": {
    "1": {"keyword": "開拓", "mission": "新しい道を切り開く役割"},
    "2": {"keyword": "基盤作り", "mission": "安定と継続の構築"},
    "3": {"keyword": "行動", "mission": "スピードと直感で進む"},
    "4": {"keyword": "努力", "mission": "積み重ねと継続の成果"},
    "5": {"keyword": "変化", "mission": "柔軟な発想で環境を動かす"},
    "6": {"keyword": "自由", "mission": "型に囚われない表現"},
    "7": {"keyword": "観察", "mission": "深い洞察で真実を見る"},
    "8": {"keyword": "現実", "mission": "実利を追う賢さ"},
    "9": {"keyword": "精神", "mission": "静けさと内面世界の探求"},
    "10": {"keyword": "多才", "mission": "複数才能の同時開花"},
    
    "11": {"keyword": "調和", "mission": "人と環境を整える"},
    "12": {"keyword": "支え", "mission": "家庭・支援の柱"},
    "13": {"keyword": "直観", "mission": "ひらめきで道を示す"},
    "14": {"keyword": "感性", "mission": "繊細さによる洞察"},
    "15": {"keyword": "社交", "mission": "人間関係の潤滑油"},

    "16": {"keyword": "理解", "mission": "構造を見抜いて最適化"},
    "17": {"keyword": "探求", "mission": "深層と本質への到達"},
    "18": {"keyword": "論理", "mission": "情報の整理と整合性"},
    "19": {"keyword": "公平", "mission": "双方を理解した調停"},
    "20": {"keyword": "静力", "mission": "静かに影響力を広げる"},

    "21": {"keyword": "使命", "mission": "導く側としての責任"},
    "22": {"keyword": "堅実", "mission": "土台作りと継続の力"},
    "23": {"keyword": "発信", "mission": "場を動かすメッセージ性"},
    "24": {"keyword": "調整", "mission": "間を繋ぎ整える司令塔"},
    "25": {"keyword": "精神性", "mission": "天命と向き合う深み"},

    "26": {"keyword": "独立", "mission": "自分のペースを極める"},
    "27": {"keyword": "こだわり", "mission": "専門性を深め極める"},
    "28": {"keyword": "創造", "mission": "新しい価値を生む"},
    "29": {"keyword": "感情", "mission": "心の流れの理解"},
    "30": {"keyword": "実務", "mission": "緻密な実行"},

    "31": {"keyword": "器の大きさ", "mission": "人を導く役割"},
    "32": {"keyword": "広さ", "mission": "視野と許容の拡大"},
    "33": {"keyword": "変革", "mission": "改革・刷新"},
    "34": {"keyword": "精神", "mission": "心のバランス"},
    "35": {"keyword": "構築", "mission": "秩序をつくる"},

    "36": {"keyword": "芸術", "mission": "表現の才能"},
    "37": {"keyword": "直観", "mission": "見えない流れを読む"},
    "38": {"keyword": "霊感", "mission": "気配・空気を読む力"},
    "39": {"keyword": "包容", "mission": "柔らかさと受容"},
    "40": {"keyword": "控えめ", "mission": "静かな強さ"},

    "41": {"keyword": "変容", "mission": "成長・変化を促す"},
    "42": {"keyword": "均衡", "mission": "全体の調和"},
    "43": {"keyword": "整理", "mission": "混乱の最適化"},
    "44": {"keyword": "深化", "mission": "深い理解"},
    "45": {"keyword": "変化感", "mission": "直感的変化"},

    "46": {"keyword": "革新", "mission": "価値の再構築"},
    "47": {"keyword": "解放", "mission": "精神的自由"},
    "48": {"keyword": "集中", "mission": "深掘りの才能"},
    "49": {"keyword": "本質", "mission": "余計なものを削ぎ落とす"},
    "50": {"keyword": "創造性", "mission": "独自の世界観"},

    "51": {"keyword": "叡智", "mission": "真理の探求"},
    "52": {"keyword": "真理", "mission": "本質への深い理解"},
    "53": {"keyword": "俯瞰", "mission": "全体統合の視点"},
    "54": {"keyword": "包容力", "mission": "人と世界を包む"},
    "55": {"keyword": "調和", "mission": "静と動の統合"},

    "56": {"keyword": "柔知", "mission": "柔らかい叡智"},
    "57": {"keyword": "内観", "mission": "心の深層への理解"},
    "58": {"keyword": "静深", "mission": "静けさの奥の洞察"},
    "59": {"keyword": "潜在", "mission": "眠る才能の開花"},
    "60": {"keyword": "悟り", "mission": "人生の統合点"}
  },

  "hand_hooks": {
    "masukake": {
      "name": "マスカケ線",
      "trait": "極端な集中・強烈な個性・天才型",
      "behavior": "一度決めると圧倒的な集中力で突き抜ける。"
    },
    "support": {
      "name": "支援型",
      "trait": "人の力になる・優しさ・裏方の才能",
      "behavior": "場の空気を読み、必要な役に回る。"
    },
    "dialog": {
      "name": "対話型",
      "trait": "コミュニケーション能力・調整役",
      "behavior": "対話を通して関係を円滑にする。"
    },
    "late": {
      "name": "晩成型",
      "trait": "時間をかけて開花・後半強い",
      "behavior": "焦らず歩むほど大きな成果を出す。"
    },
    "free": {
      "name": "自由線",
      "trait": "マイペース・個性・気まま",
      "behavior": "直感で動く軽さと自由を重視。"
    },
    "lead": {
      "name": "統率型",
      "trait": "リーダー・まとめ役・統率力",
      "behavior": "集団を自然と引っぱる。"
    }
  },

  "action_hooks": {
    "support": "支援・共感・裏方",
    "free": "自由・直感・気分で動く",
    "lead": "統率・指導・前に立つ",
    "dialog": "対話で調整・橋渡し",
    "deep": "深掘り・探求・分析",
    "plan": "計画性・準備・整える"
  }
}
